zdppy_captcha/__init__.py
zdppy_captcha/audio.py
zdppy_captcha/common.py
zdppy_captcha/data/0/default.wav
zdppy_captcha/data/1/default.wav
zdppy_captcha/data/2/default.wav
zdppy_captcha/data/3/default.wav
zdppy_captcha/data/4/default.wav
zdppy_captcha/data/5/default.wav
zdppy_captcha/data/6/default.wav
zdppy_captcha/data/7/default.wav
zdppy_captcha/data/8/default.wav
zdppy_captcha/data/9/default.wav
zdppy_captcha/data/DroidSansMono.ttf
zdppy_captcha/data/beep.wav
zdppy_captcha/image.py
zdppy_captcha/tobase64.py
zdppy_captcha/validate.py
zdppy_captcha/zdppy_api.py
zdppy_captcha-0.1.5.dist-info/LICENSE
zdppy_captcha-0.1.5.dist-info/METADATA
zdppy_captcha-0.1.5.dist-info/WHEEL
zdppy_captcha-0.1.5.dist-info/RECORD
